nn_mkdocs_strings_replacement/__init__.py
nn_mkdocs_strings_replacement/plugin.py
nn_mkdocs_strings_replacement-0.0.311111.dist-info/METADATA
nn_mkdocs_strings_replacement-0.0.311111.dist-info/WHEEL
nn_mkdocs_strings_replacement-0.0.311111.dist-info/entry_points.txt
nn_mkdocs_strings_replacement-0.0.311111.dist-info/RECORD
